pekit/__init__.py
pekit/util.py
pekit-0.1.2.dist-info/LICENSE
pekit-0.1.2.dist-info/METADATA
pekit-0.1.2.dist-info/WHEEL
pekit-0.1.2.dist-info/top_level.txt
pekit-0.1.2.dist-info/RECORD
